LICENSE.md
netapiclient/__init__.py
netapiclient-0.0.0a0.dist-info/LICENSE.md
netapiclient-0.0.0a0.dist-info/METADATA
netapiclient-0.0.0a0.dist-info/WHEEL
netapiclient-0.0.0a0.dist-info/RECORD
